CodeChat/CodeToMarkdown.py
CodeChat/CodeToPretext.py
CodeChat/CodeToRest.py
CodeChat/CodeToRestSphinx.py
CodeChat/CommentDelimiterInfo.py
CodeChat/LICENSE.rst
CodeChat/RestToCode.py
CodeChat/SourceClassifier.py
CodeChat/__init__.py
CodeChat/mdbook_CodeChat.py
CodeChat/css/CodeChat.css
CodeChat/css/CodeChat_sphinx_rtd_theme.css
CodeChat/css/__init__.py
CodeChat/css/docutils.css
CodeChat-1.9.4.dist-info/LICENSE.rst
CodeChat-1.9.4.dist-info/METADATA
CodeChat-1.9.4.dist-info/WHEEL
CodeChat-1.9.4.dist-info/entry_points.txt
CodeChat-1.9.4.dist-info/top_level.txt
CodeChat-1.9.4.dist-info/RECORD
