Metadata-Version: 2.1
Name: CodeChat
Version: 1.9.4
Summary: The CodeChat System for software documentation
Home-page: http://codechat.readthedocs.io/en/latest/
Author: Bryan A. Jones
Author-email: bjones@ece.msstate.edu
License: GPLv3+
Keywords: literate programming
Classifier: Development Status :: 5 - Production/Stable
Classifier: Intended Audience :: Developers
Classifier: License :: OSI Approved :: GNU General Public License v3 or later (GPLv3+)
Classifier: Operating System :: OS Independent
Classifier: Natural Language :: English
Classifier: Programming Language :: Python :: 3
Classifier: Programming Language :: Python :: 3.3
Classifier: Programming Language :: Python :: 3.4
Classifier: Programming Language :: Python :: 3.5
Classifier: Topic :: Software Development :: Documentation
Classifier: Topic :: Text Processing :: Markup
License-File: CodeChat/LICENSE.rst
Requires-Dist: docutils >=0.13.1
Requires-Dist: pygments >=2.1
Requires-Dist: lxml
Provides-Extra: sphinx
Requires-Dist: sphinx >=3 ; extra == 'sphinx'
Requires-Dist: myst-parser ; extra == 'sphinx'
Provides-Extra: test
Requires-Dist: pytest ; extra == 'test'
Requires-Dist: sphinx >=3 ; extra == 'test'
Requires-Dist: myst-parser ; extra == 'test'
Requires-Dist: black ; extra == 'test'
Requires-Dist: flake8 ; extra == 'test'
